revpimodio2/__about__.py
revpimodio2/__init__.py
revpimodio2/_internal.py
revpimodio2/app.py
revpimodio2/device.py
revpimodio2/errors.py
revpimodio2/helper.py
revpimodio2/io.py
revpimodio2/modio.py
revpimodio2/netio.py
revpimodio2/pictory.py
revpimodio2/summary.py
revpimodio2-2.8.0.dist-info/LICENSE.txt
revpimodio2-2.8.0.dist-info/METADATA
revpimodio2-2.8.0.dist-info/WHEEL
revpimodio2-2.8.0.dist-info/top_level.txt
revpimodio2-2.8.0.dist-info/RECORD
