Metadata-Version: 2.1
Name: revpimodio2
Version: 2.8.0
Summary: Python3 programming for RevolutionPi of KUNBUS GmbH
Home-page: https://revpimodio.org/
Author: Sven Sager
Author-email: akira@narux.de
Maintainer: Sven Sager
Maintainer-email: akira@revpimodio.org
License: LGPLv2
Keywords: revpi,revolution pi,revpimodio,plc,automation
Platform: all
Classifier: Development Status :: 5 - Production/Stable
Classifier: Environment :: Console
Classifier: Intended Audience :: Developers
Classifier: License :: OSI Approved :: GNU Lesser General Public License v2 (LGPLv2)
Classifier: Operating System :: MacOS :: MacOS X
Classifier: Operating System :: Microsoft :: Windows
Classifier: Operating System :: POSIX
Classifier: Programming Language :: Python :: 3
Classifier: Topic :: Software Development :: Libraries :: Python Modules
Requires-Python: >= 3.2
License-File: LICENSE.txt
